u_fancy/__init__.py
u_fancy/accordion_frame.py
u_fancy/bullet_points.py
u_fancy/editor_frame.py
u_fancy/profile_generator.py
u_fancy/rich_text.py
u_fancy/slideshow.py
u_fancy-0.0.2.dist-info/LICENSE
u_fancy-0.0.2.dist-info/METADATA
u_fancy-0.0.2.dist-info/WHEEL
u_fancy-0.0.2.dist-info/top_level.txt
u_fancy-0.0.2.dist-info/RECORD
